{
	"class" : {
		"comboBoxName" : "brunobb 04/09/2018 11:20" },
	"instance" : {
		"frFieldsInDocumentXpath" : "brunobb 02/27/2018 11:04",
		"frFieldsInGridXpath" : "brunobb 02/27/2018 16:16",
		"frFieldsInSectionXpath" : "brunobb 02/27/2018 09:55",
		"searchFieldsXPath" : "brunobb 02/27/2018 06:09",
		"summaryFieldsXPath" : "brunobb 02/27/2018 06:09",
		"templateClass" : "brunobb 03/05/2018 14:27",
		"usFieldsInDocumentXpath" : "brunobb 02/27/2018 11:04",
		"usFieldsInGridXpath" : "brunobb 03/07/2018 12:00",
		"usFieldsInSectionXpath" : "brunobb 02/27/2018 09:54",
		"xfFieldsInDocumentXpath" : "brunobb 02/27/2018 11:05",
		"xfFieldsInGridXpath" : "brunobb 02/27/2018 16:17",
		"xfFieldsInSectionXpath" : "brunobb 02/27/2018 09:54" } }
