{
	"class" : {
		"applicationNamed:ifNone:" : "BrunoBB 04/27/2016 14:52",
		"exampleRegistry" : "BrunoBB 04/27/2016 14:52",
		"formDefinitionNamed:in:" : "BrunoBB 04/27/2016 14:52",
		"formsDefinitionNamed:" : "BrunoBB 04/27/2016 14:52",
		"getAllDefinitionsWithId:ifNone:" : "BrunoBB 04/27/2016 14:52",
		"getAllFormDefinitions" : "BrunoBB 04/27/2016 14:52",
		"getAllInstances" : "BrunoBB 04/27/2016 14:52",
		"getAllInstancesOf:definitionNamed:" : "BrunoBB 04/27/2016 14:52",
		"getAllPublishedDefinitionNamed:fromApplicationNamed:ifNone:" : "BrunoBB 05/04/2016 13:51",
		"getAllPublishedDefinitionNamed:fromApplicationNamed:withVersion:ifNone:" : "BrunoBB 05/04/2016 13:58",
		"getAllSavedDefinitions" : "BrunoBB 04/27/2016 14:52",
		"getAnyDefinitionWithId:ifNone:" : "BrunoBB 04/27/2016 14:52",
		"getAnyDraftWith:formName:in:ifNone:" : "BrunoBB 04/27/2016 14:52",
		"getAnyInstanceWith:formName:in:ifNone:" : "BrunoBB 04/27/2016 14:52",
		"getDefinitionWithId:ifNone:" : "BrunoBB 04/27/2016 14:52",
		"getExistingApplicationOrCreateNewNamed:" : "BrunoBB 04/27/2016 15:20",
		"getInstancesCreationDayDistributionQuantityFrom:to:" : "BrunoBB 10/01/2016 10:04",
		"getInstancesCreationDayDistributionQuantityFrom:to:groupedBy:" : "BrunoBB 10/01/2016 09:58",
		"getInstancesCreationDistributionByMonthFrom:to:" : "BrunoBB 10/02/2016 11:55",
		"getInstancesModificationDayDistributionQuantityFrom:to:" : "BrunoBB 10/02/2016 12:01",
		"getInstancesModificationDayDistributionQuantityFrom:to:groupedBy:" : "BrunoBB 10/01/2016 10:39",
		"getInstancesModificationDistributionByMonthFrom:to:" : "BrunoBB 10/02/2016 11:55",
		"getInstancesQuantityFrom:to:" : "BrunoBB 10/07/2016 07:03",
		"getLastDefinitions" : "BrunoBB 04/27/2016 14:52",
		"getLastPublishedDefinitionNamed:fromApplicationNamed:withVersion:ifNone:" : "BrunoBB 05/04/2016 13:52",
		"getLatestSavedDefinition:app:" : "BrunoBB 04/30/2016 16:18",
		"getLatestSavedDefinition:app:ifNone:" : "BrunoBB 04/30/2016 17:15",
		"getNumberOfFormInstances" : "BrunoBB 10/01/2016 10:11",
		"getSavedDefinition:app:withId:" : "BrunoBB 04/27/2016 14:52",
		"getSavedDefinitionWithId:ifNone:" : "BrunoBB 04/30/2016 09:25",
		"hasFormDefinitionNamed:" : "BrunoBB 04/27/2016 14:52",
		"includesDefinitionNamed:in:" : "BrunoBB 04/27/2016 14:52",
		"initializeAllCache" : "BrunoBB 04/28/2016 11:20",
		"logicalRemoveDefinitionWithId:ifNone:" : "BrunoBB 04/27/2016 14:52",
		"reportCreationDayDistributionQuantityFrom:to:" : "BrunoBB 10/19/2016 05:50",
		"reportCreationDistributionByMonthFrom:to:satisfying:" : "BrunoBB 10/19/2016 04:33",
		"reportModificationDayDistributionQuantityFrom:to:" : "BrunoBB 10/19/2016 05:50",
		"reportModificationDistributionByMonthFrom:to:satisfying:" : "BrunoBB 10/19/2016 04:33",
		"reportQuantityDistributionFrom:to:" : "BrunoBB 10/19/2016 04:18" },
	"instance" : {
		"addPublishedDefinition:" : "BrunoBB 04/27/2016 14:52",
		"addSavedDefinition:" : "BrunoBB 04/27/2016 14:52",
		"addTestPermissions" : "BrunoBB 04/27/2016 14:52",
		"canDelete" : "BrunoBB 04/27/2016 14:52",
		"createRegistryFor:" : "BrunoBB 07/28/2016 10:35",
		"definitionNamed:" : "BrunoBB 04/27/2016 14:52",
		"definitionNamed:ifNone:" : "BrunoBB 04/27/2016 14:52",
		"definitionRegistry" : "BrunoBB 04/27/2016 14:52",
		"definitionRegistry:" : "BrunoBB 04/27/2016 14:52",
		"getAllDefinitions" : "BrunoBB 04/27/2016 14:52",
		"getAllDefinitionsNamed:" : "BrunoBB 05/04/2016 13:35",
		"getAllDefinitionsNamed:ifNone:" : "BrunoBB 04/27/2016 14:52",
		"getAllDefinitionsNamed:withVersion:ifNone:" : "BrunoBB 05/04/2016 13:48",
		"getAllInstances" : "BrunoBB 04/27/2016 14:52",
		"getAllInstancesKeysOfFormNamed:" : "BrunoBB 04/27/2016 14:52",
		"getAllSavedDefinitions" : "BrunoBB 04/27/2016 14:52",
		"getAllSearchFieldsOf:" : "BrunoBB 04/27/2016 14:52",
		"getAnyDraftWithId:of:" : "BrunoBB 04/27/2016 14:52",
		"getAnyInstanceWithId:of:" : "BrunoBB 04/27/2016 14:52",
		"getAnyInstanceWithId:of:ifNone:" : "BrunoBB 04/27/2016 14:52",
		"getApplicationNameForCombo" : "BrunoBB 04/27/2016 14:52",
		"getDefinitionNamed:withVersion:ifNone:" : "BrunoBB 04/27/2016 14:52",
		"getDefinitionWithId:ifNone:" : "BrunoBB 04/27/2016 14:52",
		"getInstancesCreationDayDistributionQuantityFrom:to:" : "BrunoBB 09/30/2016 09:19",
		"getInstancesCreationDayDistributionQuantityFrom:to:groupedBy:" : "BrunoBB 09/30/2016 10:51",
		"getInstancesCreationDistributionByMonthFrom:to:" : "BrunoBB 10/02/2016 11:46",
		"getInstancesCreationDistributionByMonthFrom:to:satisfying:" : "BrunoBB 10/07/2016 17:58",
		"getInstancesDistributionPercentage" : "BrunoBB 09/23/2016 05:25",
		"getInstancesDistributionQuantity" : "BrunoBB 09/24/2016 08:51",
		"getInstancesDistributionQuantityFrom:to:" : "BrunoBB 10/18/2016 11:39",
		"getInstancesDistributionQuantityFrom:to:satisfying:" : "BrunoBB 10/18/2016 11:38",
		"getInstancesModificationDayDistributionQuantityFrom:to:" : "BrunoBB 10/02/2016 11:41",
		"getInstancesModificationDayDistributionQuantityFrom:to:groupedBy:" : "BrunoBB 09/30/2016 10:54",
		"getInstancesModificationDistributionByMonthFrom:to:" : "BrunoBB 10/02/2016 11:33",
		"getInstancesModificationDistributionByMonthFrom:to:satisfying:" : "BrunoBB 10/07/2016 17:59",
		"getInstancesQuantityFrom:to:" : "BrunoBB 10/07/2016 06:57",
		"getLastDefinitions" : "BrunoBB 04/27/2016 14:52",
		"getLastFormDefinitionVersionOf:" : "BrunoBB 04/27/2016 14:52",
		"getLatestSavedDefinition:" : "BrunoBB 04/30/2016 17:15",
		"getLatestSavedDefinition:ifNone:" : "BrunoBB 04/30/2016 17:14",
		"getNumberOfInstances" : "BrunoBB 10/01/2016 10:11",
		"getSavedDefinitionFor:withId:ifNone:" : "BrunoBB 04/30/2016 09:21",
		"getSavedDefinitionWithId:ifNone:" : "BrunoBB 04/27/2016 14:52",
		"hasDefinitionNamed:" : "BrunoBB 04/27/2016 14:52",
		"hasReadAccess:" : "BrunoBB 04/27/2016 14:52",
		"hasRegistryFor:" : "BrunoBB 04/28/2016 11:03",
		"hasRegistryForFormNamed:" : "BrunoBB 04/27/2016 14:52",
		"initialize" : "BrunoBB 04/27/2016 14:52",
		"isObeonApplication" : "BrunoBB 08/31/2016 11:49",
		"numberOfInstances" : "BrunoBB 04/27/2016 14:52",
		"printOn:" : "BrunoBB 04/27/2016 14:52",
		"printType" : "BrunoBB 08/31/2016 12:02",
		"registryFor:" : "BrunoBB 04/28/2016 11:04",
		"registryForFormNamed:" : "BrunoBB 04/27/2016 14:52",
		"registryForFormNamed:ifNone:" : "BrunoBB 04/27/2016 14:52",
		"removeDefinition:" : "BrunoBB 04/27/2016 14:52",
		"removeInstanceDefinition:" : "BrunoBB 04/27/2016 14:52",
		"reportCreationDayDistributionQuantityFrom:to:" : "BrunoBB 10/19/2016 04:40",
		"reportCreationDistributionByMonthFrom:to:" : "BrunoBB 10/18/2016 11:47",
		"reportCreationDistributionByMonthFrom:to:satisfying:" : "BrunoBB 10/18/2016 11:43",
		"reportModificationDayDistributionQuantityFrom:to:" : "BrunoBB 10/18/2016 12:27",
		"reportModificationDistributionByMonthFrom:to:" : "BrunoBB 10/18/2016 11:47",
		"reportModificationDistributionByMonthFrom:to:satisfying:" : "BrunoBB 10/18/2016 11:44",
		"reportQuantityDistributionFrom:to:" : "BrunoBB 10/18/2016 11:31",
		"reportQuantityDistributionFrom:to:satisfying:" : "BrunoBB 10/18/2016 11:55",
		"setRegistryFormNamed:with:" : "BrunoBB 04/30/2016 15:24",
		"unregisterDefinition:" : "BrunoBB 04/27/2016 14:52",
		"unregisterDefinitionNamed:" : "BrunoBB 04/27/2016 14:52" } }
